[
    {
        "anonymous": false,
        "inputs": [
            {
                "indexed": true,
                "internalType": "address",
                "name": "manager",
                "type": "address"
            },
            {
                "indexed": true,
                "internalType": "address",
                "name": "beneficiary",
                "type": "address"
            }
        ],
        "name": "BeneficiaryAdded",
        "type": "event"
    },
    {
        "anonymous": false,
        "inputs": [
            {
                "indexed": true,
                "internalType": "address",
                "name": "beneficiary",
                "type": "address"
            },
            {
                "indexed": false,
                "internalType": "uint256",
                "name": "amount",
                "type": "uint256"
            }
        ],
        "name": "BeneficiaryClaim",
        "type": "event"
    },
    {
        "anonymous": false,
        "inputs": [
            {
                "indexed": true,
                "internalType": "address",
                "name": "beneficiary",
                "type": "address"
            }
        ],
        "name": "BeneficiaryJoined",
        "type": "event"
    },
    {
        "anonymous": false,
        "inputs": [
            {
                "indexed": true,
                "internalType": "address",
                "name": "manager",
                "type": "address"
            },
            {
                "indexed": true,
                "internalType": "address",
                "name": "beneficiary",
                "type": "address"
            }
        ],
        "name": "BeneficiaryLocked",
        "type": "event"
    },
    {
        "anonymous": false,
        "inputs": [
            {
                "indexed": false,
                "internalType": "uint256",
                "name": "oldClaimAmount",
                "type": "uint256"
            },
            {
                "indexed": false,
                "internalType": "uint256",
                "name": "oldMaxClaim",
                "type": "uint256"
            },
            {
                "indexed": false,
                "internalType": "uint256",
                "name": "oldDecreaseStep",
                "type": "uint256"
            },
            {
                "indexed": false,
                "internalType": "uint256",
                "name": "oldBaseInterval",
                "type": "uint256"
            },
            {
                "indexed": false,
                "internalType": "uint256",
                "name": "oldIncrementInterval",
                "type": "uint256"
            },
            {
                "indexed": false,
                "internalType": "uint256",
                "name": "newClaimAmount",
                "type": "uint256"
            },
            {
                "indexed": false,
                "internalType": "uint256",
                "name": "newMaxClaim",
                "type": "uint256"
            },
            {
                "indexed": false,
                "internalType": "uint256",
                "name": "newDecreaseStep",
                "type": "uint256"
            },
            {
                "indexed": false,
                "internalType": "uint256",
                "name": "newBaseInterval",
                "type": "uint256"
            },
            {
                "indexed": false,
                "internalType": "uint256",
                "name": "newIncrementInterval",
                "type": "uint256"
            }
        ],
        "name": "BeneficiaryParamsUpdated",
        "type": "event"
    },
    {
        "anonymous": false,
        "inputs": [
            {
                "indexed": true,
                "internalType": "address",
                "name": "manager",
                "type": "address"
            },
            {
                "indexed": true,
                "internalType": "address",
                "name": "beneficiary",
                "type": "address"
            }
        ],
        "name": "BeneficiaryRemoved",
        "type": "event"
    },
    {
        "anonymous": false,
        "inputs": [
            {
                "indexed": true,
                "internalType": "address",
                "name": "manager",
                "type": "address"
            },
            {
                "indexed": true,
                "internalType": "address",
                "name": "beneficiary",
                "type": "address"
            }
        ],
        "name": "BeneficiaryUnlocked",
        "type": "event"
    },
    {
        "anonymous": false,
        "inputs": [
            {
                "indexed": true,
                "internalType": "address",
                "name": "oldCommunityAdmin",
                "type": "address"
            },
            {
                "indexed": true,
                "internalType": "address",
                "name": "newCommunityAdmin",
                "type": "address"
            }
        ],
        "name": "CommunityAdminUpdated",
        "type": "event"
    },
    {
        "anonymous": false,
        "inputs": [
            {
                "indexed": true,
                "internalType": "address",
                "name": "manager",
                "type": "address"
            }
        ],
        "name": "CommunityLocked",
        "type": "event"
    },
    {
        "anonymous": false,
        "inputs": [
            {
                "indexed": false,
                "internalType": "uint256",
                "name": "oldMinTranche",
                "type": "uint256"
            },
            {
                "indexed": false,
                "internalType": "uint256",
                "name": "oldMaxTranche",
                "type": "uint256"
            },
            {
                "indexed": false,
                "internalType": "uint256",
                "name": "newMinTranche",
                "type": "uint256"
            },
            {
                "indexed": false,
                "internalType": "uint256",
                "name": "newMaxTranche",
                "type": "uint256"
            }
        ],
        "name": "CommunityParamsUpdated",
        "type": "event"
    },
    {
        "anonymous": false,
        "inputs": [
            {
                "indexed": true,
                "internalType": "address",
                "name": "manager",
                "type": "address"
            }
        ],
        "name": "CommunityUnlocked",
        "type": "event"
    },
    {
        "anonymous": false,
        "inputs": [
            {
                "indexed": true,
                "internalType": "address",
                "name": "donor",
                "type": "address"
            },
            {
                "indexed": false,
                "internalType": "uint256",
                "name": "amount",
                "type": "uint256"
            }
        ],
        "name": "Donate",
        "type": "event"
    },
    {
        "anonymous": false,
        "inputs": [
            {
                "indexed": true,
                "internalType": "address",
                "name": "manager",
                "type": "address"
            }
        ],
        "name": "FundsRequested",
        "type": "event"
    },
    {
        "anonymous": false,
        "inputs": [
            {
                "indexed": true,
                "internalType": "address",
                "name": "manager",
                "type": "address"
            },
            {
                "indexed": true,
                "internalType": "address",
                "name": "account",
                "type": "address"
            }
        ],
        "name": "ManagerAdded",
        "type": "event"
    },
    {
        "anonymous": false,
        "inputs": [
            {
                "indexed": true,
                "internalType": "address",
                "name": "manager",
                "type": "address"
            },
            {
                "indexed": true,
                "internalType": "address",
                "name": "account",
                "type": "address"
            }
        ],
        "name": "ManagerRemoved",
        "type": "event"
    },
    {
        "anonymous": false,
        "inputs": [
            {
                "indexed": true,
                "internalType": "address",
                "name": "previousOwner",
                "type": "address"
            },
            {
                "indexed": true,
                "internalType": "address",
                "name": "newOwner",
                "type": "address"
            }
        ],
        "name": "OwnershipTransferred",
        "type": "event"
    },
    {
        "anonymous": false,
        "inputs": [
            {
                "indexed": true,
                "internalType": "address",
                "name": "oldPreviousCommunity",
                "type": "address"
            },
            {
                "indexed": true,
                "internalType": "address",
                "name": "newPreviousCommunity",
                "type": "address"
            }
        ],
        "name": "PreviousCommunityUpdated",
        "type": "event"
    },
    {
        "anonymous": false,
        "inputs": [
            {
                "indexed": true,
                "internalType": "bytes32",
                "name": "role",
                "type": "bytes32"
            },
            {
                "indexed": true,
                "internalType": "bytes32",
                "name": "previousAdminRole",
                "type": "bytes32"
            },
            {
                "indexed": true,
                "internalType": "bytes32",
                "name": "newAdminRole",
                "type": "bytes32"
            }
        ],
        "name": "RoleAdminChanged",
        "type": "event"
    },
    {
        "anonymous": false,
        "inputs": [
            {
                "indexed": true,
                "internalType": "bytes32",
                "name": "role",
                "type": "bytes32"
            },
            {
                "indexed": true,
                "internalType": "address",
                "name": "account",
                "type": "address"
            },
            {
                "indexed": true,
                "internalType": "address",
                "name": "sender",
                "type": "address"
            }
        ],
        "name": "RoleGranted",
        "type": "event"
    },
    {
        "anonymous": false,
        "inputs": [
            {
                "indexed": true,
                "internalType": "bytes32",
                "name": "role",
                "type": "bytes32"
            },
            {
                "indexed": true,
                "internalType": "address",
                "name": "account",
                "type": "address"
            },
            {
                "indexed": true,
                "internalType": "address",
                "name": "sender",
                "type": "address"
            }
        ],
        "name": "RoleRevoked",
        "type": "event"
    },
    {
        "anonymous": false,
        "inputs": [
            {
                "indexed": true,
                "internalType": "address",
                "name": "token",
                "type": "address"
            },
            {
                "indexed": true,
                "internalType": "address",
                "name": "to",
                "type": "address"
            },
            {
                "indexed": false,
                "internalType": "uint256",
                "name": "amount",
                "type": "uint256"
            }
        ],
        "name": "TransferERC20",
        "type": "event"
    },
    {
        "inputs": [],
        "name": "DEFAULT_ADMIN_ROLE",
        "outputs": [
            {
                "internalType": "bytes32",
                "name": "",
                "type": "bytes32"
            }
        ],
        "stateMutability": "view",
        "type": "function"
    },
    {
        "inputs": [],
        "name": "_firstBlockTimestamp",
        "outputs": [
            {
                "internalType": "uint256",
                "name": "",
                "type": "uint256"
            }
        ],
        "stateMutability": "view",
        "type": "function"
    },
    {
        "inputs": [
            {
                "internalType": "address",
                "name": "",
                "type": "address"
            }
        ],
        "name": "claimed",
        "outputs": [
            {
                "internalType": "uint256",
                "name": "",
                "type": "uint256"
            }
        ],
        "stateMutability": "view",
        "type": "function"
    },
    {
        "inputs": [
            {
                "internalType": "address",
                "name": "",
                "type": "address"
            }
        ],
        "name": "cooldown",
        "outputs": [
            {
                "internalType": "uint256",
                "name": "",
                "type": "uint256"
            }
        ],
        "stateMutability": "view",
        "type": "function"
    },
    {
        "inputs": [
            {
                "internalType": "address",
                "name": "beneficiaryAddress_",
                "type": "address"
            }
        ],
        "name": "addBeneficiary",
        "outputs": [],
        "stateMutability": "nonpayable",
        "type": "function"
    },
    {
        "inputs": [
            {
                "internalType": "address",
                "name": "account_",
                "type": "address"
            }
        ],
        "name": "addManager",
        "outputs": [],
        "stateMutability": "nonpayable",
        "type": "function"
    },
    {
        "inputs": [
            {
                "internalType": "uint256",
                "name": "amount_",
                "type": "uint256"
            }
        ],
        "name": "addTreasuryFunds",
        "outputs": [],
        "stateMutability": "nonpayable",
        "type": "function"
    },
    {
        "inputs": [],
        "name": "baseInterval",
        "outputs": [
            {
                "internalType": "uint256",
                "name": "",
                "type": "uint256"
            }
        ],
        "stateMutability": "view",
        "type": "function"
    },
    {
        "inputs": [
            {
                "internalType": "address",
                "name": "",
                "type": "address"
            }
        ],
        "name": "beneficiaries",
        "outputs": [
            {
                "internalType": "enum ICommunity.BeneficiaryState",
                "name": "state",
                "type": "uint8"
            },
            {
                "internalType": "uint256",
                "name": "claims",
                "type": "uint256"
            },
            {
                "internalType": "uint256",
                "name": "claimedAmount",
                "type": "uint256"
            },
            {
                "internalType": "uint256",
                "name": "lastClaim",
                "type": "uint256"
            }
        ],
        "stateMutability": "view",
        "type": "function"
    },
    {
        "inputs": [],
        "name": "beneficiaryJoinFromMigrated",
        "outputs": [],
        "stateMutability": "nonpayable",
        "type": "function"
    },
    {
        "inputs": [
            {
                "internalType": "uint256",
                "name": "index_",
                "type": "uint256"
            }
        ],
        "name": "beneficiaryListAt",
        "outputs": [
            {
                "internalType": "address",
                "name": "",
                "type": "address"
            }
        ],
        "stateMutability": "view",
        "type": "function"
    },
    {
        "inputs": [],
        "name": "beneficiaryListLength",
        "outputs": [
            {
                "internalType": "uint256",
                "name": "",
                "type": "uint256"
            }
        ],
        "stateMutability": "view",
        "type": "function"
    },
    {
        "inputs": [],
        "name": "cUSD",
        "outputs": [
            {
                "internalType": "contract IERC20",
                "name": "",
                "type": "address"
            }
        ],
        "stateMutability": "view",
        "type": "function"
    },
    {
        "inputs": [],
        "name": "claim",
        "outputs": [],
        "stateMutability": "nonpayable",
        "type": "function"
    },
    {
        "inputs": [],
        "name": "claimAmount",
        "outputs": [
            {
                "internalType": "uint256",
                "name": "",
                "type": "uint256"
            }
        ],
        "stateMutability": "view",
        "type": "function"
    },
    {
        "inputs": [
            {
                "internalType": "address",
                "name": "beneficiaryAddress_",
                "type": "address"
            }
        ],
        "name": "claimCooldown",
        "outputs": [
            {
                "internalType": "uint256",
                "name": "",
                "type": "uint256"
            }
        ],
        "stateMutability": "view",
        "type": "function"
    },
    {
        "inputs": [],
        "name": "communityAdmin",
        "outputs": [
            {
                "internalType": "contract ICommunityAdmin",
                "name": "",
                "type": "address"
            }
        ],
        "stateMutability": "view",
        "type": "function"
    },
    {
        "inputs": [],
        "name": "decreaseStep",
        "outputs": [
            {
                "internalType": "uint256",
                "name": "",
                "type": "uint256"
            }
        ],
        "stateMutability": "view",
        "type": "function"
    },
    {
        "inputs": [
            {
                "internalType": "address",
                "name": "sender_",
                "type": "address"
            },
            {
                "internalType": "uint256",
                "name": "amount_",
                "type": "uint256"
            }
        ],
        "name": "donate",
        "outputs": [],
        "stateMutability": "nonpayable",
        "type": "function"
    },
    {
        "inputs": [],
        "name": "getInitialMaxClaim",
        "outputs": [
            {
                "internalType": "uint256",
                "name": "",
                "type": "uint256"
            }
        ],
        "stateMutability": "view",
        "type": "function"
    },
    {
        "inputs": [
            {
                "internalType": "bytes32",
                "name": "role",
                "type": "bytes32"
            }
        ],
        "name": "getRoleAdmin",
        "outputs": [
            {
                "internalType": "bytes32",
                "name": "",
                "type": "bytes32"
            }
        ],
        "stateMutability": "view",
        "type": "function"
    },
    {
        "inputs": [],
        "name": "getVersion",
        "outputs": [
            {
                "internalType": "uint256",
                "name": "",
                "type": "uint256"
            }
        ],
        "stateMutability": "pure",
        "type": "function"
    },
    {
        "inputs": [
            {
                "internalType": "bytes32",
                "name": "role",
                "type": "bytes32"
            },
            {
                "internalType": "address",
                "name": "account",
                "type": "address"
            }
        ],
        "name": "grantRole",
        "outputs": [],
        "stateMutability": "nonpayable",
        "type": "function"
    },
    {
        "inputs": [
            {
                "internalType": "bytes32",
                "name": "role",
                "type": "bytes32"
            },
            {
                "internalType": "address",
                "name": "account",
                "type": "address"
            }
        ],
        "name": "hasRole",
        "outputs": [
            {
                "internalType": "bool",
                "name": "",
                "type": "bool"
            }
        ],
        "stateMutability": "view",
        "type": "function"
    },
    {
        "inputs": [],
        "name": "impactMarketAddress",
        "outputs": [
            {
                "internalType": "address",
                "name": "",
                "type": "address"
            }
        ],
        "stateMutability": "pure",
        "type": "function"
    },
    {
        "inputs": [],
        "name": "incrementInterval",
        "outputs": [
            {
                "internalType": "uint256",
                "name": "",
                "type": "uint256"
            }
        ],
        "stateMutability": "view",
        "type": "function"
    },
    {
        "inputs": [
            {
                "internalType": "address[]",
                "name": "managers_",
                "type": "address[]"
            },
            {
                "internalType": "uint256",
                "name": "claimAmount_",
                "type": "uint256"
            },
            {
                "internalType": "uint256",
                "name": "maxClaim_",
                "type": "uint256"
            },
            {
                "internalType": "uint256",
                "name": "decreaseStep_",
                "type": "uint256"
            },
            {
                "internalType": "uint256",
                "name": "baseInterval_",
                "type": "uint256"
            },
            {
                "internalType": "uint256",
                "name": "incrementInterval_",
                "type": "uint256"
            },
            {
                "internalType": "uint256",
                "name": "minTranche_",
                "type": "uint256"
            },
            {
                "internalType": "uint256",
                "name": "maxTranche_",
                "type": "uint256"
            },
            {
                "internalType": "contract ICommunity",
                "name": "previousCommunity_",
                "type": "address"
            }
        ],
        "name": "initialize",
        "outputs": [],
        "stateMutability": "nonpayable",
        "type": "function"
    },
    {
        "inputs": [
            {
                "internalType": "address",
                "name": "beneficiaryAddress_",
                "type": "address"
            }
        ],
        "name": "lastInterval",
        "outputs": [
            {
                "internalType": "uint256",
                "name": "",
                "type": "uint256"
            }
        ],
        "stateMutability": "view",
        "type": "function"
    },
    {
        "inputs": [],
        "name": "lock",
        "outputs": [],
        "stateMutability": "nonpayable",
        "type": "function"
    },
    {
        "inputs": [
            {
                "internalType": "address",
                "name": "beneficiaryAddress_",
                "type": "address"
            }
        ],
        "name": "lockBeneficiary",
        "outputs": [],
        "stateMutability": "nonpayable",
        "type": "function"
    },
    {
        "inputs": [],
        "name": "locked",
        "outputs": [
            {
                "internalType": "bool",
                "name": "",
                "type": "bool"
            }
        ],
        "stateMutability": "view",
        "type": "function"
    },
    {
        "inputs": [],
        "name": "maxClaim",
        "outputs": [
            {
                "internalType": "uint256",
                "name": "",
                "type": "uint256"
            }
        ],
        "stateMutability": "view",
        "type": "function"
    },
    {
        "inputs": [],
        "name": "maxTranche",
        "outputs": [
            {
                "internalType": "uint256",
                "name": "",
                "type": "uint256"
            }
        ],
        "stateMutability": "view",
        "type": "function"
    },
    {
        "inputs": [],
        "name": "minTranche",
        "outputs": [
            {
                "internalType": "uint256",
                "name": "",
                "type": "uint256"
            }
        ],
        "stateMutability": "view",
        "type": "function"
    },
    {
        "inputs": [],
        "name": "owner",
        "outputs": [
            {
                "internalType": "address",
                "name": "",
                "type": "address"
            }
        ],
        "stateMutability": "view",
        "type": "function"
    },
    {
        "inputs": [],
        "name": "previousCommunity",
        "outputs": [
            {
                "internalType": "contract ICommunity",
                "name": "",
                "type": "address"
            }
        ],
        "stateMutability": "view",
        "type": "function"
    },
    {
        "inputs": [],
        "name": "privateFunds",
        "outputs": [
            {
                "internalType": "uint256",
                "name": "",
                "type": "uint256"
            }
        ],
        "stateMutability": "view",
        "type": "function"
    },
    {
        "inputs": [
            {
                "internalType": "address",
                "name": "beneficiaryAddress_",
                "type": "address"
            }
        ],
        "name": "removeBeneficiary",
        "outputs": [],
        "stateMutability": "nonpayable",
        "type": "function"
    },
    {
        "inputs": [
            {
                "internalType": "address",
                "name": "account_",
                "type": "address"
            }
        ],
        "name": "removeManager",
        "outputs": [],
        "stateMutability": "nonpayable",
        "type": "function"
    },
    {
        "inputs": [],
        "name": "renounceOwnership",
        "outputs": [],
        "stateMutability": "nonpayable",
        "type": "function"
    },
    {
        "inputs": [
            {
                "internalType": "bytes32",
                "name": "role",
                "type": "bytes32"
            },
            {
                "internalType": "address",
                "name": "account",
                "type": "address"
            }
        ],
        "name": "renounceRole",
        "outputs": [],
        "stateMutability": "nonpayable",
        "type": "function"
    },
    {
        "inputs": [],
        "name": "requestFunds",
        "outputs": [],
        "stateMutability": "nonpayable",
        "type": "function"
    },
    {
        "inputs": [
            {
                "internalType": "bytes32",
                "name": "role",
                "type": "bytes32"
            },
            {
                "internalType": "address",
                "name": "account",
                "type": "address"
            }
        ],
        "name": "revokeRole",
        "outputs": [],
        "stateMutability": "nonpayable",
        "type": "function"
    },
    {
        "inputs": [
            {
                "internalType": "bytes4",
                "name": "interfaceId",
                "type": "bytes4"
            }
        ],
        "name": "supportsInterface",
        "outputs": [
            {
                "internalType": "bool",
                "name": "",
                "type": "bool"
            }
        ],
        "stateMutability": "view",
        "type": "function"
    },
    {
        "inputs": [
            {
                "internalType": "contract IERC20",
                "name": "token_",
                "type": "address"
            },
            {
                "internalType": "address",
                "name": "to_",
                "type": "address"
            },
            {
                "internalType": "uint256",
                "name": "amount_",
                "type": "uint256"
            }
        ],
        "name": "transfer",
        "outputs": [],
        "stateMutability": "nonpayable",
        "type": "function"
    },
    {
        "inputs": [
            {
                "internalType": "address",
                "name": "newOwner",
                "type": "address"
            }
        ],
        "name": "transferOwnership",
        "outputs": [],
        "stateMutability": "nonpayable",
        "type": "function"
    },
    {
        "inputs": [],
        "name": "treasuryFunds",
        "outputs": [
            {
                "internalType": "uint256",
                "name": "",
                "type": "uint256"
            }
        ],
        "stateMutability": "view",
        "type": "function"
    },
    {
        "inputs": [],
        "name": "unlock",
        "outputs": [],
        "stateMutability": "nonpayable",
        "type": "function"
    },
    {
        "inputs": [
            {
                "internalType": "address",
                "name": "beneficiaryAddress_",
                "type": "address"
            }
        ],
        "name": "unlockBeneficiary",
        "outputs": [],
        "stateMutability": "nonpayable",
        "type": "function"
    },
    {
        "inputs": [
            {
                "internalType": "uint256",
                "name": "claimAmount_",
                "type": "uint256"
            },
            {
                "internalType": "uint256",
                "name": "maxClaim_",
                "type": "uint256"
            },
            {
                "internalType": "uint256",
                "name": "decreaseStep_",
                "type": "uint256"
            },
            {
                "internalType": "uint256",
                "name": "baseInterval_",
                "type": "uint256"
            },
            {
                "internalType": "uint256",
                "name": "incrementInterval_",
                "type": "uint256"
            }
        ],
        "name": "updateBeneficiaryParams",
        "outputs": [],
        "stateMutability": "nonpayable",
        "type": "function"
    },
    {
        "inputs": [
            {
                "internalType": "contract ICommunityAdmin",
                "name": "newCommunityAdmin_",
                "type": "address"
            }
        ],
        "name": "updateCommunityAdmin",
        "outputs": [],
        "stateMutability": "nonpayable",
        "type": "function"
    },
    {
        "inputs": [
            {
                "internalType": "uint256",
                "name": "minTranche_",
                "type": "uint256"
            },
            {
                "internalType": "uint256",
                "name": "maxTranche_",
                "type": "uint256"
            }
        ],
        "name": "updateCommunityParams",
        "outputs": [],
        "stateMutability": "nonpayable",
        "type": "function"
    },
    {
        "inputs": [
            {
                "internalType": "contract ICommunity",
                "name": "newPreviousCommunity_",
                "type": "address"
            }
        ],
        "name": "updatePreviousCommunity",
        "outputs": [],
        "stateMutability": "nonpayable",
        "type": "function"
    },
    {
        "inputs": [],
        "name": "validBeneficiaryCount",
        "outputs": [
            {
                "internalType": "uint256",
                "name": "",
                "type": "uint256"
            }
        ],
        "stateMutability": "view",
        "type": "function"
    }
]
